README.md
setup.cfg
setup.py
TAS_Transmission_Atom_Surface.egg-info/PKG-INFO
TAS_Transmission_Atom_Surface.egg-info/SOURCES.txt
TAS_Transmission_Atom_Surface.egg-info/dependency_links.txt
TAS_Transmission_Atom_Surface.egg-info/not-zip-safe
TAS_Transmission_Atom_Surface.egg-info/top_level.txt
tas/__init__.py
tas/tas.py