Metadata-Version: 2.1
Name: TAS-Transmission-Atom-Surface
Version: 0.0.3
Summary: TAS - Transmission spectra with Atom-Surface interactions
Home-page: UNKNOWN
Author: Tom Peyrot and Nikola Sibalic
Author-email: nikolasibalic@physics.org
License: BSD3
Download-URL: https://github.com/thermal-vapours/TAS-Transmission-Atom-Surface/archive/0.0.3.tar.gz
Keywords: van der Waals,atom surface interactions,alkali atoms,spectroscopy,scientific,physics,laser spectroscopy,thin atomic vapours
Platform: UNKNOWN
